foggy_training/__init__.py
foggy_training/addons/__init__.py
foggy_training/addons/transforms.py
foggy_training/base/__init__.py
foggy_training/base/lookups.py
foggy_training/base/model.py
foggy_training/config.py
foggy_training/datasets/__init__.py
foggy_training/datasets/dataset.py
foggy_training/models/__init__.py
foggy_training/models/models.py
foggy_training/wrapper/__init__.py
foggy_training/wrapper/wrapper.py
foggy_training-0.1.162.dist-info/WHEEL
foggy_training-0.1.162.dist-info/METADATA
foggy_training-0.1.162.dist-info/RECORD
