Metadata-Version: 2.1
Name: foggy-training
Version: 0.1.162
Summary: 
Author: JanDiers
Author-email: jan.diers@uni-jena.de
Requires-Python: >=3.8,<4.0
Classifier: Programming Language :: Python :: 3
Classifier: Programming Language :: Python :: 3.10
Classifier: Programming Language :: Python :: 3.8
Classifier: Programming Language :: Python :: 3.9
Requires-Dist: attrs (>=22.1.0,<23.0.0)
Requires-Dist: torchinfo (>=1.7.1,<2.0.0)
